{"web":{"auth_uri":"https://accounts.google.com/o/oauth2/auth","client_secret":"mvRaVYB0_8v5BzOm9q03p-YV","token_uri":"https://accounts.google.com/o/oauth2/token","client_email":"156485760688-ph4gap85euq0u174vf57dh99s35qc2mg@developer.gserviceaccount.com","redirect_uris":["https://www.example.com/oauth2callback","http://localhost:8080/oauth2callback"],"client_x509_cert_url":"https://www.googleapis.com/robot/v1/metadata/x509/156485760688-ph4gap85euq0u174vf57dh99s35qc2mg@developer.gserviceaccount.com","client_id":"156485760688-ph4gap85euq0u174vf57dh99s35qc2mg.apps.googleusercontent.com","auth_provider_x509_cert_url":"https://www.googleapis.com/oauth2/v1/certs","javascript_origins":["https://www.example.com","http://localhost:8080"]}}